caseconverter/__init__.py
caseconverter/caseconverter.py
caseconverter/caseconverter_test.py
case_converter-1.0.4.dist-info/LICENSE
case_converter-1.0.4.dist-info/METADATA
case_converter-1.0.4.dist-info/WHEEL
case_converter-1.0.4.dist-info/top_level.txt
case_converter-1.0.4.dist-info/RECORD
