Metadata-Version: 2.1
Name: case-converter
Version: 1.0.4
Summary: A string case conversion package.
Home-page: https://github.com/chrisdoherty4/python-case-converter
Author: Chris Doherty
Author-email: chris@chrisdoherty.io
License: UNKNOWN
Keywords: case,convert,converter,string
Platform: UNKNOWN
Classifier: Development Status :: 5 - Production/Stable
Classifier: License :: OSI Approved :: MIT License
Classifier: Natural Language :: English
Classifier: Topic :: Utilities
Classifier: Topic :: Text Processing
Classifier: Programming Language :: Python :: 3
License-File: LICENSE
